index.py
setup.py
nodeman/__init__.py
nodeman/config.py
nodeman/utils.py
nodeman.egg-info/PKG-INFO
nodeman.egg-info/SOURCES.txt
nodeman.egg-info/dependency_links.txt
nodeman.egg-info/entry_points.txt
nodeman.egg-info/requires.txt
nodeman.egg-info/top_level.txt