Metadata-Version: 1.0
Name: nodeman
Version: 0.5.1
Summary: CLI tool to manage Node.js binaries
Home-page: https://github.com/mujx/nodeman
Author: mujx
Author-email: siderisk@auth.gr
License: MIT
Platform: UNKNOWN
